{
    "dex": [
        {
            "symbol": "HYPE",
            "spread": 18.49,
            "buyAt": "ETH",
            "sellAt": "MEXC",
            "dex_price": "32.72774311",
            "cex_price": "38.78000000",
            "liquidity": "$191467648"
        },
        {
            "symbol": "CORE",
            "spread": 1.54,
            "buyAt": "ETH",
            "sellAt": "MEXC",
            "dex_price": "0.03212420",
            "cex_price": "0.03262000",
            "liquidity": "$33730435"
        },
        {
            "symbol": "TAO",
            "spread": 1.2,
            "buyAt": "ETH",
            "sellAt": "MEXC",
            "dex_price": "313.45892535",
            "cex_price": "317.22000000",
            "liquidity": "$1914212"
        },
        {
            "symbol": "LOL",
            "spread": 1.11,
            "buyAt": "SOLANA",
            "sellAt": "MEXC",
            "dex_price": "0.00832720",
            "cex_price": "0.00842000",
            "liquidity": "$313354"
        },
        {
            "symbol": "VRA",
            "spread": 0.93,
            "buyAt": "ETH",
            "sellAt": "MEXC",
            "dex_price": "0.00003815",
            "cex_price": "0.00003850",
            "liquidity": "$69408"
        },
        {
            "symbol": "PIPPIN",
            "spread": 0.51,
            "buyAt": "SOLANA",
            "sellAt": "MEXC",
            "dex_price": "0.05224392",
            "cex_price": "0.05251200",
            "liquidity": "$5367961"
        },
        {
            "symbol": "PEPU",
            "spread": 0.47,
            "buyAt": "ETH",
            "sellAt": "MEXC",
            "dex_price": "0.00010949",
            "cex_price": "0.00011000",
            "liquidity": "$238508"
        },
        {
            "symbol": "KEKIUS",
            "spread": 0.44,
            "buyAt": "ETH",
            "sellAt": "MEXC",
            "dex_price": "0.00849865",
            "cex_price": "0.00853600",
            "liquidity": "$893783"
        },
        {
            "symbol": "SIREN",
            "spread": 0.44,
            "buyAt": "BSC",
            "sellAt": "MEXC",
            "dex_price": "1.69847605",
            "cex_price": "1.70600000",
            "liquidity": "$14742824"
        },
        {
            "symbol": "BTC",
            "spread": 0.4,
            "buyAt": "ETH",
            "sellAt": "MEXC",
            "dex_price": "66163.80702200",
            "cex_price": "66430.24000000",
            "liquidity": "$44580657"
        },
        {
            "symbol": "PEPE",
            "spread": 0.39,
            "buyAt": "ETH",
            "sellAt": "MEXC",
            "dex_price": "0.00000325",
            "cex_price": "0.00000326",
            "liquidity": "$23198586"
        }
    ],
    "spot": [],
    "futures": []
}