{
    "dex": [
        {
            "symbol": "RAVE",
            "spread": 13.61,
            "buyAt": "BSC",
            "sellAt": "MEXC",
            "dex_price": "0.32241140",
            "cex_price": "0.36630000",
            "liquidity": "$1425780"
        },
        {
            "symbol": "IN",
            "spread": 10.16,
            "buyAt": "BSC",
            "sellAt": "MEXC",
            "dex_price": "0.06633039",
            "cex_price": "0.07307000",
            "liquidity": "$2111541"
        },
        {
            "symbol": "TJR",
            "spread": 7.5,
            "buyAt": "SOLANA",
            "sellAt": "MEXC",
            "dex_price": "0.00104647",
            "cex_price": "0.00112500",
            "liquidity": "$94972"
        },
        {
            "symbol": "AERO",
            "spread": 0.86,
            "buyAt": "BASE",
            "sellAt": "MEXC",
            "dex_price": "0.46819670",
            "cex_price": "0.47220000",
            "liquidity": "$25919783"
        },
        {
            "symbol": "H",
            "spread": 0.67,
            "buyAt": "ETH",
            "sellAt": "MEXC",
            "dex_price": "0.08961669",
            "cex_price": "0.09022000",
            "liquidity": "$27179"
        },
        {
            "symbol": "LAB",
            "spread": 0.65,
            "buyAt": "BSC",
            "sellAt": "MEXC",
            "dex_price": "13.73053996",
            "cex_price": "13.82000000",
            "liquidity": "$149247"
        },
        {
            "symbol": "GITLAWB",
            "spread": 0.55,
            "buyAt": "BASE",
            "sellAt": "MEXC",
            "dex_price": "0.00004255",
            "cex_price": "0.00004278",
            "liquidity": "$1595325"
        },
        {
            "symbol": "KINS",
            "spread": 0.43,
            "buyAt": "SOLANA",
            "sellAt": "MEXC",
            "dex_price": "0.01352299",
            "cex_price": "0.01358100",
            "liquidity": "$430013"
        },
        {
            "symbol": "CAP",
            "spread": 0.33,
            "buyAt": "BSC",
            "sellAt": "MEXC",
            "dex_price": "0.02968316",
            "cex_price": "0.02978000",
            "liquidity": "$952817"
        },
        {
            "symbol": "BTW",
            "spread": 0.33,
            "buyAt": "BSC",
            "sellAt": "MEXC",
            "dex_price": "0.05145270",
            "cex_price": "0.05162300",
            "liquidity": "$1227546"
        },
        {
            "symbol": "SKYAI",
            "spread": 0.31,
            "buyAt": "BSC",
            "sellAt": "MEXC",
            "dex_price": "0.10895773",
            "cex_price": "0.10930000",
            "liquidity": "$7314620"
        },
        {
            "symbol": "VELVET",
            "spread": 0.3,
            "buyAt": "BASE",
            "sellAt": "MEXC",
            "dex_price": "1.66342136",
            "cex_price": "1.66843000",
            "liquidity": "$9334460"
        },
        {
            "symbol": "BTC",
            "spread": 0.21,
            "buyAt": "ARBITRUM",
            "sellAt": "MEXC",
            "dex_price": "58510.02812951",
            "cex_price": "58631.83000000",
            "liquidity": "$28545480"
        },
        {
            "symbol": "SLX",
            "spread": 0.2,
            "buyAt": "BSC",
            "sellAt": "MEXC",
            "dex_price": "0.54818489",
            "cex_price": "0.54930000",
            "liquidity": "$1236538"
        }
    ],
    "spot": [],
    "futures": []
}