{
    "dex": [
        {
            "symbol": "SIREN",
            "spread": 0.66,
            "buyAt": "BSC",
            "sellAt": "MEXC",
            "dex_price": "1.68296693",
            "cex_price": "1.69400000",
            "liquidity": "$14656652"
        },
        {
            "symbol": "PUNCH",
            "spread": 0.63,
            "buyAt": "SOLANA",
            "sellAt": "MEXC",
            "dex_price": "0.01331677",
            "cex_price": "0.01340100",
            "liquidity": "$714282"
        },
        {
            "symbol": "PENGUIN",
            "spread": 0.62,
            "buyAt": "SOLANA",
            "sellAt": "MEXC",
            "dex_price": "0.00348435",
            "cex_price": "0.00350600",
            "liquidity": "$329495"
        },
        {
            "symbol": "CHIBI",
            "spread": 0.45,
            "buyAt": "SOLANA",
            "sellAt": "MEXC",
            "dex_price": "0.00090551",
            "cex_price": "0.00090960",
            "liquidity": "$107799"
        },
        {
            "symbol": "TAO",
            "spread": 0.41,
            "buyAt": "ETH",
            "sellAt": "MEXC",
            "dex_price": "320.21512355",
            "cex_price": "321.52000000",
            "liquidity": "$1948530"
        },
        {
            "symbol": "LINK",
            "spread": 0.3,
            "buyAt": "ETH",
            "sellAt": "MEXC",
            "dex_price": "8.61082940",
            "cex_price": "8.63700000",
            "liquidity": "$21161998"
        },
        {
            "symbol": "BSB",
            "spread": 0.27,
            "buyAt": "BSC",
            "sellAt": "MEXC",
            "dex_price": "0.19951177",
            "cex_price": "0.20005000",
            "liquidity": "$12115251"
        },
        {
            "symbol": "RIVER",
            "spread": 0.27,
            "buyAt": "BSC",
            "sellAt": "MEXC",
            "dex_price": "14.58338309",
            "cex_price": "14.62230000",
            "liquidity": "$1015350"
        },
        {
            "symbol": "Q",
            "spread": 0.26,
            "buyAt": "BSC",
            "sellAt": "MEXC",
            "dex_price": "0.00875554",
            "cex_price": "0.00877800",
            "liquidity": "$628976"
        }
    ],
    "spot": [],
    "futures": []
}