{
    "dex": [
        {
            "symbol": "SWEAT",
            "spread": 38.45,
            "buyAt": "ETH",
            "sellAt": "MEXC",
            "dex_price": "0.00184368",
            "cex_price": "0.00255250",
            "liquidity": "$498702"
        },
        {
            "symbol": "WKC",
            "spread": 3.6,
            "buyAt": "BSC",
            "sellAt": "MEXC",
            "dex_price": "0.00000008",
            "cex_price": "0.00000008",
            "liquidity": "$1122948"
        },
        {
            "symbol": "KISHU",
            "spread": 2.73,
            "buyAt": "ETH",
            "sellAt": "MEXC",
            "dex_price": "0.00000000",
            "cex_price": "0.00000000",
            "liquidity": "$1015886"
        },
        {
            "symbol": "SERAPH",
            "spread": 2.06,
            "buyAt": "BSC",
            "sellAt": "MEXC",
            "dex_price": "0.01245567",
            "cex_price": "0.01271200",
            "liquidity": "$323372"
        },
        {
            "symbol": "HANTA",
            "spread": 1.77,
            "buyAt": "SOLANA",
            "sellAt": "MEXC",
            "dex_price": "0.00353728",
            "cex_price": "0.00360000",
            "liquidity": "$251386"
        },
        {
            "symbol": "AI",
            "spread": 1.33,
            "buyAt": "ETH",
            "sellAt": "MEXC",
            "dex_price": "0.03773983",
            "cex_price": "0.03824000",
            "liquidity": "$1692662"
        },
        {
            "symbol": "PTB",
            "spread": 0.75,
            "buyAt": "BSC",
            "sellAt": "MEXC",
            "dex_price": "0.00097802",
            "cex_price": "0.00098540",
            "liquidity": "$169548"
        },
        {
            "symbol": "BILL",
            "spread": 0.59,
            "buyAt": "BSC",
            "sellAt": "MEXC",
            "dex_price": "0.10366234",
            "cex_price": "0.10427000",
            "liquidity": "$1958788"
        },
        {
            "symbol": "ONDO",
            "spread": 0.47,
            "buyAt": "ETH",
            "sellAt": "MEXC",
            "dex_price": "0.40755214",
            "cex_price": "0.40947000",
            "liquidity": "$657502"
        },
        {
            "symbol": "SIREN",
            "spread": 0.26,
            "buyAt": "BSC",
            "sellAt": "MEXC",
            "dex_price": "1.22805081",
            "cex_price": "1.23130000",
            "liquidity": "$12551854"
        }
    ],
    "spot": [],
    "futures": []
}