{
    "dex": [
        {
            "symbol": "DOGEUS",
            "spread": 1.15,
            "buyAt": "ETH",
            "sellAt": "MEXC",
            "dex_price": "0.00035145",
            "cex_price": "0.00035550",
            "liquidity": "$71300"
        },
        {
            "symbol": "TAC",
            "spread": 1.0,
            "buyAt": "BSC",
            "sellAt": "MEXC",
            "dex_price": "0.00248207",
            "cex_price": "0.00250700",
            "liquidity": "$163257"
        },
        {
            "symbol": "SKYAI",
            "spread": 0.5,
            "buyAt": "BSC",
            "sellAt": "MEXC",
            "dex_price": "0.03196939",
            "cex_price": "0.03213000",
            "liquidity": "$4094046"
        },
        {
            "symbol": "ANSEM",
            "spread": 0.29,
            "buyAt": "SOLANA",
            "sellAt": "MEXC",
            "dex_price": "0.30170004",
            "cex_price": "0.30257000",
            "liquidity": "$2767402"
        }
    ],
    "spot": [],
    "futures": []
}