{
    "dex": [
        {
            "symbol": "KISHU",
            "spread": 4.68,
            "buyAt": "ETH",
            "sellAt": "MEXC",
            "dex_price": "0.00000000",
            "cex_price": "0.00000000",
            "liquidity": "$1674912"
        },
        {
            "symbol": "WKC",
            "spread": 3.09,
            "buyAt": "BSC",
            "sellAt": "MEXC",
            "dex_price": "0.00000008",
            "cex_price": "0.00000008",
            "liquidity": "$1156580"
        },
        {
            "symbol": "SATO",
            "spread": 2.01,
            "buyAt": "ETH",
            "sellAt": "MEXC",
            "dex_price": "0.88322157",
            "cex_price": "0.90100000",
            "liquidity": "$1681379"
        },
        {
            "symbol": "AI",
            "spread": 1.94,
            "buyAt": "ETH",
            "sellAt": "MEXC",
            "dex_price": "0.04013189",
            "cex_price": "0.04091000",
            "liquidity": "$1625505"
        },
        {
            "symbol": "SIREN",
            "spread": 1.11,
            "buyAt": "BSC",
            "sellAt": "MEXC",
            "dex_price": "0.54543790",
            "cex_price": "0.55150000",
            "liquidity": "$7954720"
        },
        {
            "symbol": "LAB",
            "spread": 0.68,
            "buyAt": "BSC",
            "sellAt": "MEXC",
            "dex_price": "5.75642933",
            "cex_price": "5.79570000",
            "liquidity": "$120620"
        },
        {
            "symbol": "SKYAI",
            "spread": 0.2,
            "buyAt": "BSC",
            "sellAt": "MEXC",
            "dex_price": "0.37524621",
            "cex_price": "0.37600000",
            "liquidity": "$13941733"
        }
    ],
    "spot": [],
    "futures": []
}