{
    "dex": [
        {
            "symbol": "GMEBULL",
            "spread": 0.84,
            "buyAt": "SOLANA",
            "sellAt": "MEXC",
            "dex_price": "0.00030543",
            "cex_price": "0.00030800",
            "liquidity": "$48519"
        },
        {
            "symbol": "ZAMA",
            "spread": 0.62,
            "buyAt": "BSC",
            "sellAt": "MEXC",
            "dex_price": "0.05534644",
            "cex_price": "0.05569000",
            "liquidity": "$1352318"
        },
        {
            "symbol": "ON",
            "spread": 0.53,
            "buyAt": "BSC",
            "sellAt": "MEXC",
            "dex_price": "0.17467819",
            "cex_price": "0.17560000",
            "liquidity": "$1013990"
        },
        {
            "symbol": "AAVE",
            "spread": 0.49,
            "buyAt": "ETH",
            "sellAt": "MEXC",
            "dex_price": "95.61151820",
            "cex_price": "96.08000000",
            "liquidity": "$11700"
        },
        {
            "symbol": "B2",
            "spread": 0.42,
            "buyAt": "BSC",
            "sellAt": "MEXC",
            "dex_price": "0.31969316",
            "cex_price": "0.32104000",
            "liquidity": "$630570"
        },
        {
            "symbol": "BTC",
            "spread": 0.25,
            "buyAt": "ETH",
            "sellAt": "MEXC",
            "dex_price": "64635.85591382",
            "cex_price": "64795.21000000",
            "liquidity": "$13209033"
        }
    ],
    "spot": [],
    "futures": []
}