{
    "dex": [
        {
            "symbol": "TJR",
            "spread": 31.58,
            "buyAt": "SOLANA",
            "sellAt": "MEXC",
            "dex_price": "0.00079341",
            "cex_price": "0.00104400",
            "liquidity": "$82048"
        },
        {
            "symbol": "HOODON",
            "spread": 24.46,
            "buyAt": "ETH",
            "sellAt": "MEXC",
            "dex_price": "79.77450471",
            "cex_price": "99.29000000",
            "liquidity": "$1349769"
        },
        {
            "symbol": "RAVE",
            "spread": 15.11,
            "buyAt": "BSC",
            "sellAt": "MEXC",
            "dex_price": "0.31585979",
            "cex_price": "0.36360000",
            "liquidity": "$1412382"
        },
        {
            "symbol": "IN",
            "spread": 8.35,
            "buyAt": "BSC",
            "sellAt": "MEXC",
            "dex_price": "0.06494946",
            "cex_price": "0.07037000",
            "liquidity": "$2093873"
        },
        {
            "symbol": "TSLAON",
            "spread": 5.37,
            "buyAt": "ETH",
            "sellAt": "MEXC",
            "dex_price": "394.20120824",
            "cex_price": "415.37000000",
            "liquidity": "$8245894"
        },
        {
            "symbol": "BTW",
            "spread": 0.58,
            "buyAt": "BSC",
            "sellAt": "MEXC",
            "dex_price": "0.05892994",
            "cex_price": "0.05927400",
            "liquidity": "$1253436"
        },
        {
            "symbol": "SPX",
            "spread": 0.37,
            "buyAt": "ETH",
            "sellAt": "MEXC",
            "dex_price": "0.33207516",
            "cex_price": "0.33330000",
            "liquidity": "$8152111"
        },
        {
            "symbol": "H",
            "spread": 0.31,
            "buyAt": "ETH",
            "sellAt": "MEXC",
            "dex_price": "0.08707243",
            "cex_price": "0.08734000",
            "liquidity": "$26962"
        },
        {
            "symbol": "TAC",
            "spread": 0.28,
            "buyAt": "BSC",
            "sellAt": "MEXC",
            "dex_price": "0.06327370",
            "cex_price": "0.06344800",
            "liquidity": "$1260135"
        },
        {
            "symbol": "BTC",
            "spread": 0.22,
            "buyAt": "ETH",
            "sellAt": "MEXC",
            "dex_price": "58320.61957051",
            "cex_price": "58449.38000000",
            "liquidity": "$11608493"
        },
        {
            "symbol": "SLX",
            "spread": 0.21,
            "buyAt": "BSC",
            "sellAt": "MEXC",
            "dex_price": "0.47182311",
            "cex_price": "0.47280000",
            "liquidity": "$1213435"
        }
    ],
    "spot": [],
    "futures": []
}