{
    "dex": [
        {
            "symbol": "CASHCAT",
            "spread": 0.8,
            "buyAt": "SOLANA",
            "sellAt": "MEXC",
            "dex_price": "0.12648933",
            "cex_price": "0.12750000",
            "liquidity": "$122278"
        },
        {
            "symbol": "UPEG",
            "spread": 0.6,
            "buyAt": "ETH",
            "sellAt": "MEXC",
            "dex_price": "181.71923250",
            "cex_price": "182.81000000",
            "liquidity": "$565834"
        },
        {
            "symbol": "MOG",
            "spread": 0.45,
            "buyAt": "ETH",
            "sellAt": "MEXC",
            "dex_price": "0.00000011",
            "cex_price": "0.00000011",
            "liquidity": "$4702813"
        },
        {
            "symbol": "BILL",
            "spread": 0.3,
            "buyAt": "BSC",
            "sellAt": "MEXC",
            "dex_price": "0.03407703",
            "cex_price": "0.03418000",
            "liquidity": "$1595480"
        },
        {
            "symbol": "USDC",
            "spread": 0.28,
            "buyAt": "ARBITRUM",
            "sellAt": "MEXC",
            "dex_price": "0.99791448",
            "cex_price": "1.00075000",
            "liquidity": "$564006729"
        },
        {
            "symbol": "PEPE",
            "spread": 0.26,
            "buyAt": "ETH",
            "sellAt": "MEXC",
            "dex_price": "0.00000287",
            "cex_price": "0.00000287",
            "liquidity": "$21587553"
        },
        {
            "symbol": "TRIA",
            "spread": 0.24,
            "buyAt": "BSC",
            "sellAt": "MEXC",
            "dex_price": "0.00825034",
            "cex_price": "0.00827000",
            "liquidity": "$898521"
        },
        {
            "symbol": "LINK",
            "spread": 0.22,
            "buyAt": "ETH",
            "sellAt": "MEXC",
            "dex_price": "8.58571595",
            "cex_price": "8.60500000",
            "liquidity": "$21914331"
        },
        {
            "symbol": "BTC",
            "spread": 0.21,
            "buyAt": "ETH",
            "sellAt": "MEXC",
            "dex_price": "65297.42447857",
            "cex_price": "65431.52000000",
            "liquidity": "$41336844"
        },
        {
            "symbol": "LIT",
            "spread": 0.21,
            "buyAt": "ETH",
            "sellAt": "MEXC",
            "dex_price": "2.55025876",
            "cex_price": "2.55570000",
            "liquidity": "$618889"
        }
    ],
    "spot": [],
    "futures": []
}