{
    "dex": [
        {
            "symbol": "OGN",
            "spread": 18.1,
            "buyAt": "ETH",
            "sellAt": "MEXC",
            "dex_price": "0.02607222",
            "cex_price": "0.03079000",
            "liquidity": "$18315853"
        },
        {
            "symbol": "SN3",
            "spread": 2.57,
            "buyAt": "BSC",
            "sellAt": "MEXC",
            "dex_price": "0.00748721",
            "cex_price": "0.00768000",
            "liquidity": "$497424"
        },
        {
            "symbol": "PUNCH",
            "spread": 0.91,
            "buyAt": "SOLANA",
            "sellAt": "MEXC",
            "dex_price": "0.00553271",
            "cex_price": "0.00558300",
            "liquidity": "$424765"
        },
        {
            "symbol": "PEPE",
            "spread": 0.53,
            "buyAt": "ETH",
            "sellAt": "MEXC",
            "dex_price": "0.00000329",
            "cex_price": "0.00000330",
            "liquidity": "$23660880"
        },
        {
            "symbol": "AAVE",
            "spread": 0.45,
            "buyAt": "ETH",
            "sellAt": "MEXC",
            "dex_price": "108.81592617",
            "cex_price": "109.31000000",
            "liquidity": "$6890668"
        },
        {
            "symbol": "LYN",
            "spread": 0.38,
            "buyAt": "BSC",
            "sellAt": "MEXC",
            "dex_price": "0.16078565",
            "cex_price": "0.16139000",
            "liquidity": "$461017"
        },
        {
            "symbol": "CRTR",
            "spread": 0.34,
            "buyAt": "BSC",
            "sellAt": "MEXC",
            "dex_price": "0.05101453",
            "cex_price": "0.05119000",
            "liquidity": "$1848533"
        },
        {
            "symbol": "PENGU",
            "spread": 0.32,
            "buyAt": "SOLANA",
            "sellAt": "MEXC",
            "dex_price": "0.00703917",
            "cex_price": "0.00706200",
            "liquidity": "$27645"
        }
    ],
    "spot": [],
    "futures": []
}