{
    "dex": [
        {
            "symbol": "GWEI",
            "spread": 1.99,
            "buyAt": "ETH",
            "sellAt": "MEXC",
            "dex_price": "0.03328630",
            "cex_price": "0.03395000",
            "liquidity": "$85387"
        },
        {
            "symbol": "POWER",
            "spread": 1.76,
            "buyAt": "ETH",
            "sellAt": "MEXC",
            "dex_price": "1.40972881",
            "cex_price": "1.43456000",
            "liquidity": "$9124"
        },
        {
            "symbol": "CFG",
            "spread": 1.03,
            "buyAt": "ETH",
            "sellAt": "MEXC",
            "dex_price": "0.12402490",
            "cex_price": "0.12530000",
            "liquidity": "$670432"
        },
        {
            "symbol": "KEKIUS",
            "spread": 0.94,
            "buyAt": "ETH",
            "sellAt": "MEXC",
            "dex_price": "0.00928975",
            "cex_price": "0.00937700",
            "liquidity": "$937987"
        },
        {
            "symbol": "ROBO",
            "spread": 0.83,
            "buyAt": "BSC",
            "sellAt": "MEXC",
            "dex_price": "0.03606048",
            "cex_price": "0.03636000",
            "liquidity": "$1166884"
        },
        {
            "symbol": "ZAMA",
            "spread": 0.46,
            "buyAt": "BSC",
            "sellAt": "MEXC",
            "dex_price": "0.02332277",
            "cex_price": "0.02343000",
            "liquidity": "$947062"
        }
    ],
    "spot": [],
    "futures": []
}