{
    "dex": [
        {
            "symbol": "ION",
            "spread": 1.86,
            "buyAt": "BSC",
            "sellAt": "MEXC",
            "dex_price": "0.00203997",
            "cex_price": "0.00207800",
            "liquidity": "$874464"
        },
        {
            "symbol": "TRIA",
            "spread": 1.23,
            "buyAt": "BSC",
            "sellAt": "MEXC",
            "dex_price": "0.03642055",
            "cex_price": "0.03687000",
            "liquidity": "$1514348"
        },
        {
            "symbol": "CHIBI",
            "spread": 0.99,
            "buyAt": "SOLANA",
            "sellAt": "MEXC",
            "dex_price": "0.00138326",
            "cex_price": "0.00139700",
            "liquidity": "$129970"
        },
        {
            "symbol": "PUNCH",
            "spread": 0.59,
            "buyAt": "SOLANA",
            "sellAt": "MEXC",
            "dex_price": "0.01266054",
            "cex_price": "0.01273500",
            "liquidity": "$712808"
        }
    ],
    "spot": [],
    "futures": []
}