{
    "dex": [
        {
            "symbol": "UAI",
            "spread": 6.26,
            "buyAt": "BSC",
            "sellAt": "MEXC",
            "dex_price": "0.51751936",
            "cex_price": "0.54990000",
            "liquidity": "$1459689"
        },
        {
            "symbol": "BARD",
            "spread": 3.22,
            "buyAt": "ETH",
            "sellAt": "MEXC",
            "dex_price": "0.54066418",
            "cex_price": "0.55810000",
            "liquidity": "$5002"
        },
        {
            "symbol": "TESTICLE",
            "spread": 1.03,
            "buyAt": "SOLANA",
            "sellAt": "MEXC",
            "dex_price": "0.00782068",
            "cex_price": "0.00790100",
            "liquidity": "$545960"
        },
        {
            "symbol": "NPC",
            "spread": 0.75,
            "buyAt": "ETH",
            "sellAt": "MEXC",
            "dex_price": "0.00901749",
            "cex_price": "0.00908500",
            "liquidity": "$36090083"
        },
        {
            "symbol": "OPN",
            "spread": 0.52,
            "buyAt": "BSC",
            "sellAt": "MEXC",
            "dex_price": "0.28711485",
            "cex_price": "0.28860000",
            "liquidity": "$859197"
        },
        {
            "symbol": "LYN",
            "spread": 0.47,
            "buyAt": "BSC",
            "sellAt": "MEXC",
            "dex_price": "0.08409706",
            "cex_price": "0.08449000",
            "liquidity": "$327379"
        },
        {
            "symbol": "TRIA",
            "spread": 0.27,
            "buyAt": "BSC",
            "sellAt": "MEXC",
            "dex_price": "0.03947291",
            "cex_price": "0.03958000",
            "liquidity": "$1543754"
        }
    ],
    "spot": [],
    "futures": []
}