{
    "dex": [
        {
            "symbol": "BTC",
            "spread": 0.65,
            "buyAt": "ETH",
            "sellAt": "MEXC",
            "dex_price": "67367.64282338",
            "cex_price": "67802.21000000",
            "liquidity": "$16673235"
        },
        {
            "symbol": "PENGUIN",
            "spread": 0.65,
            "buyAt": "SOLANA",
            "sellAt": "MEXC",
            "dex_price": "0.00932196",
            "cex_price": "0.00938300",
            "liquidity": "$505165"
        },
        {
            "symbol": "BABYDOGE",
            "spread": 0.59,
            "buyAt": "BSC",
            "sellAt": "MEXC",
            "dex_price": "0.00000000",
            "cex_price": "0.00000000",
            "liquidity": "$8320736"
        },
        {
            "symbol": "MOG",
            "spread": 0.39,
            "buyAt": "ETH",
            "sellAt": "MEXC",
            "dex_price": "0.00000017",
            "cex_price": "0.00000017",
            "liquidity": "$5922746"
        },
        {
            "symbol": "ETH",
            "spread": 0.29,
            "buyAt": "ETH",
            "sellAt": "MEXC",
            "dex_price": "1968.61529288",
            "cex_price": "1974.29000000",
            "liquidity": "$85971702"
        },
        {
            "symbol": "PEPE",
            "spread": 0.23,
            "buyAt": "ETH",
            "sellAt": "MEXC",
            "dex_price": "0.00000421",
            "cex_price": "0.00000422",
            "liquidity": "$26140060"
        }
    ],
    "spot": [],
    "futures": []
}