{
    "dex": [
        {
            "symbol": "LO0P",
            "spread": 7.7,
            "buyAt": "ETH",
            "sellAt": "MEXC",
            "dex_price": "1.09252231",
            "cex_price": "1.17660000",
            "liquidity": "$385920"
        },
        {
            "symbol": "DN",
            "spread": 1.0,
            "buyAt": "BSC",
            "sellAt": "MEXC",
            "dex_price": "0.21504574",
            "cex_price": "0.21719000",
            "liquidity": "$604869"
        },
        {
            "symbol": "BTC",
            "spread": 0.35,
            "buyAt": "ETH",
            "sellAt": "MEXC",
            "dex_price": "77434.91999100",
            "cex_price": "77702.13000000",
            "liquidity": "$52484818"
        },
        {
            "symbol": "ASTEROID",
            "spread": 0.24,
            "buyAt": "ETH",
            "sellAt": "MEXC",
            "dex_price": "0.00031981",
            "cex_price": "0.00032057",
            "liquidity": "$3498964"
        },
        {
            "symbol": "PEPE",
            "spread": 0.24,
            "buyAt": "ETH",
            "sellAt": "MEXC",
            "dex_price": "0.00000372",
            "cex_price": "0.00000372",
            "liquidity": "$25771049"
        },
        {
            "symbol": "RKC",
            "spread": 0.23,
            "buyAt": "SOLANA",
            "sellAt": "MEXC",
            "dex_price": "0.00628779",
            "cex_price": "0.00630200",
            "liquidity": "$359305"
        }
    ],
    "spot": [],
    "futures": []
}