{
    "dex": [
        {
            "symbol": "RAVE",
            "spread": 22.58,
            "buyAt": "BSC",
            "sellAt": "MEXC",
            "dex_price": "0.42324979",
            "cex_price": "0.51880000",
            "liquidity": "$1599222"
        },
        {
            "symbol": "SYN",
            "spread": 1.48,
            "buyAt": "ETH",
            "sellAt": "MEXC",
            "dex_price": "0.53092446",
            "cex_price": "0.53878000",
            "liquidity": "$211548"
        },
        {
            "symbol": "THREE",
            "spread": 0.75,
            "buyAt": "SOLANA",
            "sellAt": "MEXC",
            "dex_price": "0.00282973",
            "cex_price": "0.00285100",
            "liquidity": "$254524"
        },
        {
            "symbol": "SKYAI",
            "spread": 0.6,
            "buyAt": "BSC",
            "sellAt": "MEXC",
            "dex_price": "0.12524691",
            "cex_price": "0.12600000",
            "liquidity": "$7955616"
        },
        {
            "symbol": "UB",
            "spread": 0.39,
            "buyAt": "BSC",
            "sellAt": "MEXC",
            "dex_price": "0.11661839",
            "cex_price": "0.11707000",
            "liquidity": "$3645562"
        },
        {
            "symbol": "TAC",
            "spread": 0.38,
            "buyAt": "BSC",
            "sellAt": "MEXC",
            "dex_price": "0.05852340",
            "cex_price": "0.05874700",
            "liquidity": "$1207287"
        },
        {
            "symbol": "BTC",
            "spread": 0.37,
            "buyAt": "ETH",
            "sellAt": "MEXC",
            "dex_price": "60316.54568851",
            "cex_price": "60537.45000000",
            "liquidity": "$40904931"
        },
        {
            "symbol": "SPX",
            "spread": 0.36,
            "buyAt": "ETH",
            "sellAt": "MEXC",
            "dex_price": "0.35990072",
            "cex_price": "0.36120000",
            "liquidity": "$8627489"
        },
        {
            "symbol": "ETH",
            "spread": 0.23,
            "buyAt": "ETH",
            "sellAt": "MEXC",
            "dex_price": "1621.96301762",
            "cex_price": "1625.65000000",
            "liquidity": "$82233315"
        },
        {
            "symbol": "VELVET",
            "spread": 0.22,
            "buyAt": "BSC",
            "sellAt": "MEXC",
            "dex_price": "1.69645613",
            "cex_price": "1.70015000",
            "liquidity": "$7104434"
        }
    ],
    "spot": [],
    "futures": []
}