{
    "dex": [
        {
            "symbol": "BUTTCOIN",
            "spread": 1.09,
            "buyAt": "SOLANA",
            "sellAt": "MEXC",
            "dex_price": "0.01341844",
            "cex_price": "0.01356500",
            "liquidity": "$552948"
        },
        {
            "symbol": "ZAMA",
            "spread": 0.53,
            "buyAt": "ETH",
            "sellAt": "MEXC",
            "dex_price": "0.01985482",
            "cex_price": "0.01996000",
            "liquidity": "$924402"
        },
        {
            "symbol": "BABYDOGE",
            "spread": 0.38,
            "buyAt": "BSC",
            "sellAt": "MEXC",
            "dex_price": "0.00000000",
            "cex_price": "0.00000000",
            "liquidity": "$8097032"
        },
        {
            "symbol": "BTC",
            "spread": 0.35,
            "buyAt": "ETH",
            "sellAt": "MEXC",
            "dex_price": "67635.08243956",
            "cex_price": "67870.78000000",
            "liquidity": "$45855842"
        },
        {
            "symbol": "ASTER",
            "spread": 0.27,
            "buyAt": "BSC",
            "sellAt": "MEXC",
            "dex_price": "0.70279806",
            "cex_price": "0.70470000",
            "liquidity": "$1638695"
        }
    ],
    "spot": [],
    "futures": []
}