{
    "dex": [
        {
            "symbol": "GIGGLE",
            "spread": 14.18,
            "buyAt": "ETH",
            "sellAt": "MEXC",
            "dex_price": "26.97568419",
            "cex_price": "30.80000000",
            "liquidity": "$13491247"
        },
        {
            "symbol": "CAP",
            "spread": 0.43,
            "buyAt": "BSC",
            "sellAt": "MEXC",
            "dex_price": "0.02206480",
            "cex_price": "0.02216000",
            "liquidity": "$870380"
        }
    ],
    "spot": [],
    "futures": []
}