{
    "dex": [
        {
            "symbol": "WKC",
            "spread": 3.84,
            "buyAt": "BSC",
            "sellAt": "MEXC",
            "dex_price": "0.00000007",
            "cex_price": "0.00000008",
            "liquidity": "$1085240"
        },
        {
            "symbol": "SAPIEN",
            "spread": 1.87,
            "buyAt": "ETH",
            "sellAt": "MEXC",
            "dex_price": "0.07579466",
            "cex_price": "0.07721000",
            "liquidity": "$38319343"
        },
        {
            "symbol": "THE",
            "spread": 0.63,
            "buyAt": "BSC",
            "sellAt": "MEXC",
            "dex_price": "0.21364629",
            "cex_price": "0.21500000",
            "liquidity": "$416828"
        },
        {
            "symbol": "OPN",
            "spread": 0.32,
            "buyAt": "BSC",
            "sellAt": "MEXC",
            "dex_price": "0.33352901",
            "cex_price": "0.33460000",
            "liquidity": "$942239"
        }
    ],
    "spot": [],
    "futures": []
}